{
    "frame_0.jpg": [],
    "frame_1.jpg": [],
    "frame_10.jpg": [],
    "frame_100.jpg": [
        "person"
    ],
    "frame_101.jpg": [
        "person"
    ],
    "frame_102.jpg": [],
    "frame_103.jpg": [],
    "frame_104.jpg": [
        "frisbee"
    ],
    "frame_105.jpg": [
        "kite"
    ],
    "frame_106.jpg": [],
    "frame_107.jpg": [
        "scissors"
    ],
    "frame_108.jpg": [
        "person"
    ],
    "frame_109.jpg": [
        "person",
        "baseball bat"
    ],
    "frame_11.jpg": [],
    "frame_110.jpg": [],
    "frame_111.jpg": [],
    "frame_112.jpg": [],
    "frame_113.jpg": [
        "person",
        "bowl"
    ],
    "frame_114.jpg": [],
    "frame_115.jpg": [
        "kite"
    ],
    "frame_116.jpg": [
        "kite"
    ],
    "frame_117.jpg": [],
    "frame_118.jpg": [],
    "frame_119.jpg": [],
    "frame_12.jpg": [],
    "frame_120.jpg": [
        "kite",
        "toothbrush",
        "scissors"
    ],
    "frame_121.jpg": [
        "toothbrush"
    ],
    "frame_122.jpg": [
        "toothbrush"
    ],
    "frame_123.jpg": [
        "toothbrush"
    ],
    "frame_124.jpg": [
        "person"
    ],
    "frame_125.jpg": [
        "person"
    ],
    "frame_126.jpg": [
        "sports ball"
    ],
    "frame_127.jpg": [],
    "frame_128.jpg": [],
    "frame_129.jpg": [
        "person"
    ],
    "frame_13.jpg": [],
    "frame_130.jpg": [],
    "frame_131.jpg": [],
    "frame_132.jpg": [],
    "frame_133.jpg": [],
    "frame_134.jpg": [],
    "frame_135.jpg": [],
    "frame_136.jpg": [
        "person"
    ],
    "frame_137.jpg": [],
    "frame_138.jpg": [
        "baseball glove",
        "cake"
    ],
    "frame_139.jpg": [],
    "frame_14.jpg": [
        "person"
    ],
    "frame_140.jpg": [],
    "frame_141.jpg": [
        "person"
    ],
    "frame_142.jpg": [
        "person"
    ],
    "frame_143.jpg": [
        "person"
    ],
    "frame_144.jpg": [],
    "frame_145.jpg": [
        "person"
    ],
    "frame_146.jpg": [
        "person"
    ],
    "frame_147.jpg": [
        "person",
        "clock"
    ],
    "frame_148.jpg": [
        "clock"
    ],
    "frame_149.jpg": [],
    "frame_15.jpg": [],
    "frame_150.jpg": [
        "person"
    ],
    "frame_151.jpg": [
        "person"
    ],
    "frame_152.jpg": [],
    "frame_153.jpg": [
        "person"
    ],
    "frame_154.jpg": [
        "kite"
    ],
    "frame_155.jpg": [
        "kite"
    ],
    "frame_156.jpg": [],
    "frame_157.jpg": [],
    "frame_158.jpg": [
        "person"
    ],
    "frame_159.jpg": [],
    "frame_16.jpg": [
        "person"
    ],
    "frame_160.jpg": [],
    "frame_161.jpg": [
        "person"
    ],
    "frame_162.jpg": [
        "vase"
    ],
    "frame_163.jpg": [],
    "frame_164.jpg": [
        "chair",
        "sports ball",
        "dining table"
    ],
    "frame_165.jpg": [
        "bird",
        "surfboard"
    ],
    "frame_166.jpg": [],
    "frame_167.jpg": [],
    "frame_168.jpg": [],
    "frame_169.jpg": [],
    "frame_17.jpg": [],
    "frame_170.jpg": [
        "person"
    ],
    "frame_171.jpg": [
        "cup"
    ],
    "frame_172.jpg": [],
    "frame_173.jpg": [],
    "frame_174.jpg": [
        "person",
        "vase",
        "surfboard"
    ],
    "frame_175.jpg": [
        "person",
        "airplane"
    ],
    "frame_176.jpg": [],
    "frame_177.jpg": [
        "person",
        "skateboard"
    ],
    "frame_178.jpg": [
        "person"
    ],
    "frame_179.jpg": [],
    "frame_18.jpg": [
        "vase"
    ],
    "frame_180.jpg": [],
    "frame_181.jpg": [],
    "frame_182.jpg": [
        "person",
        "cake"
    ],
    "frame_183.jpg": [
        "person",
        "sink"
    ],
    "frame_184.jpg": [
        "person"
    ],
    "frame_185.jpg": [
        "person",
        "sink"
    ],
    "frame_186.jpg": [
        "sink",
        "person"
    ],
    "frame_187.jpg": [
        "vase"
    ],
    "frame_188.jpg": [
        "person"
    ],
    "frame_189.jpg": [],
    "frame_19.jpg": [
        "person",
        "sports ball"
    ],
    "frame_190.jpg": [],
    "frame_191.jpg": [
        "person"
    ],
    "frame_192.jpg": [
        "person"
    ],
    "frame_193.jpg": [
        "person",
        "sports ball"
    ],
    "frame_194.jpg": [
        "person"
    ],
    "frame_195.jpg": [
        "person"
    ],
    "frame_196.jpg": [
        "scissors"
    ],
    "frame_197.jpg": [],
    "frame_198.jpg": [
        "cake"
    ],
    "frame_199.jpg": [],
    "frame_2.jpg": [
        "toothbrush",
        "dog"
    ],
    "frame_20.jpg": [],
    "frame_21.jpg": [
        "person"
    ],
    "frame_22.jpg": [],
    "frame_23.jpg": [
        "kite"
    ],
    "frame_24.jpg": [
        "kite"
    ],
    "frame_25.jpg": [
        "kite"
    ],
    "frame_26.jpg": [
        "kite",
        "person"
    ],
    "frame_27.jpg": [
        "kite",
        "person"
    ],
    "frame_28.jpg": [
        "kite",
        "person"
    ],
    "frame_29.jpg": [
        "kite",
        "person"
    ],
    "frame_3.jpg": [],
    "frame_30.jpg": [
        "person",
        "sports ball"
    ],
    "frame_31.jpg": [
        "person"
    ],
    "frame_32.jpg": [
        "kite",
        "person"
    ],
    "frame_33.jpg": [
        "person"
    ],
    "frame_34.jpg": [],
    "frame_35.jpg": [
        "person"
    ],
    "frame_36.jpg": [
        "person"
    ],
    "frame_37.jpg": [
        "person",
        "sports ball"
    ],
    "frame_38.jpg": [
        "person",
        "teddy bear"
    ],
    "frame_39.jpg": [
        "kite",
        "person"
    ],
    "frame_4.jpg": [],
    "frame_40.jpg": [
        "person"
    ],
    "frame_41.jpg": [
        "person"
    ],
    "frame_42.jpg": [
        "person"
    ],
    "frame_43.jpg": [],
    "frame_44.jpg": [],
    "frame_45.jpg": [],
    "frame_46.jpg": [
        "kite"
    ],
    "frame_47.jpg": [
        "dog"
    ],
    "frame_48.jpg": [
        "person",
        "fire hydrant"
    ],
    "frame_49.jpg": [
        "person"
    ],
    "frame_5.jpg": [],
    "frame_50.jpg": [
        "person"
    ],
    "frame_51.jpg": [
        "person"
    ],
    "frame_52.jpg": [
        "person"
    ],
    "frame_53.jpg": [
        "kite",
        "person"
    ],
    "frame_54.jpg": [
        "person",
        "potted plant"
    ],
    "frame_55.jpg": [
        "potted plant"
    ],
    "frame_56.jpg": [
        "person"
    ],
    "frame_57.jpg": [
        "kite"
    ],
    "frame_58.jpg": [
        "airplane",
        "surfboard"
    ],
    "frame_59.jpg": [
        "person",
        "vase"
    ],
    "frame_6.jpg": [],
    "frame_60.jpg": [],
    "frame_61.jpg": [
        "suitcase"
    ],
    "frame_62.jpg": [
        "bird"
    ],
    "frame_63.jpg": [
        "clock",
        "stop sign"
    ],
    "frame_64.jpg": [
        "traffic light"
    ],
    "frame_65.jpg": [
        "traffic light"
    ],
    "frame_66.jpg": [
        "traffic light",
        "stop sign"
    ],
    "frame_67.jpg": [
        "traffic light"
    ],
    "frame_68.jpg": [
        "traffic light"
    ],
    "frame_69.jpg": [
        "person"
    ],
    "frame_7.jpg": [],
    "frame_70.jpg": [
        "person"
    ],
    "frame_71.jpg": [
        "person"
    ],
    "frame_72.jpg": [
        "person",
        "cake",
        "dining table"
    ],
    "frame_73.jpg": [
        "cake"
    ],
    "frame_74.jpg": [
        "dining table",
        "person",
        "bowl",
        "cake"
    ],
    "frame_75.jpg": [
        "dining table",
        "person",
        "bowl",
        "cake"
    ],
    "frame_76.jpg": [
        "person"
    ],
    "frame_77.jpg": [
        "person"
    ],
    "frame_78.jpg": [],
    "frame_79.jpg": [],
    "frame_8.jpg": [],
    "frame_80.jpg": [],
    "frame_81.jpg": [],
    "frame_82.jpg": [],
    "frame_83.jpg": [],
    "frame_84.jpg": [],
    "frame_85.jpg": [],
    "frame_86.jpg": [],
    "frame_87.jpg": [
        "teddy bear",
        "sports ball"
    ],
    "frame_88.jpg": [
        "teddy bear"
    ],
    "frame_89.jpg": [],
    "frame_9.jpg": [],
    "frame_90.jpg": [
        "person",
        "tennis racket"
    ],
    "frame_91.jpg": [],
    "frame_92.jpg": [],
    "frame_93.jpg": [],
    "frame_94.jpg": [],
    "frame_95.jpg": [],
    "frame_96.jpg": [],
    "frame_97.jpg": [],
    "frame_98.jpg": [],
    "frame_99.jpg": [
        "person"
    ]
}